{
  "name": "number field",
  "inputs": {
    "value": {
      "type": "number",
      "optional": true
    },
    "style": {
      "type": "object",
      "optional": true,
      "metadata": {
        "examples": ["{fontSize:'30px'}", "{}"]
      }
    },
    "attr": {
      "type": "object",
      "optional": true,
      "metadata": {
        "examples": ["{}"]
      }
    },
    "min": {
      "type": "number",
      "optional": true,
      "defaultIgnored": true
    },
    "max": {
      "type": "number",
      "optional": true,
      "defaultIgnored": true
    }
  },
  "outputs": {
    "value": {
      "type": "number",
      "optional": true
    }
  },
  "metadata": {
    "icon": "form-input",
    "description": "single line number input",
    "tags": ["platform", "component", "value"]
  },
  "id": "9bc56564-ef4e-11ea-939a-27ae3feb321e",
  "base": true,
  "component": {
    "defaultWidth": 120,
    "defaultHeight": 45
  },
  "type": "`U`&`C`&`V`&`J`",
  "render": true
}
