{
  "name": "to blob",
  "inputs": {
    "canvas": {
      "type": "`CA`",
      "ref": true
    },
    "quality": {
      "type": "number",
      "metadata": {
        "examples": ["1"]
      }
    },
    "type": {
      "type": "string",
      "metadata": {
        "examples": ["'image/png'"]
      }
    },
    "done": {
      "type": "any"
    }
  },
  "outputs": {
    "blob": {
      "type": "`B`",
      "ref": true,
      "icon": "file"
    }
  },
  "metadata": {
    "icon": "edit-3",
    "description": "get `blob` from `canvas`",
    "link": "https://developer.mozilla.org/en-US/docs/Web/API/HTMLCanvasElement/toBlob",
    "tags": ["platform", "api", "canvas"]
  },
  "id": "c9d64ef4-35f6-44e7-a16b-1e4173f951dc",
  "base": true,
  "type": "`U`",
  "system": true
}
