{
  "name": "exec",
  "inputs": {
    "unit": {
      "type": "`U`",
      "ref": true
    },
    "method": {
      "type": "string"
    },
    "args": {
      "type": "any[]"
    }
  },
  "outputs": {
    "return": {
      "type": "any"
    }
  },
  "metadata": {
    "icon": "circle",
    "description": "execute `unit` `method` with `data`",
    "complexity": 3,
    "tags": [
      "f",
      "meta"
    ]
  },
  "id": "56fb9a32-ad10-11ea-b0f4-3b0ea5e3ac2c",
  "private": true,
  "base": true,
  "type": "`U`",
  "system": true
}